{
	"entries": [
		{
				"message": "Running Master2_HongKong.script",
				"identifier": "START",
				"timestamp": "2022-03-01 16:35:40.219 +0530"
			},
		{
				"handlerName": "on_launch",
				"timestamp": "2022-03-01 16:35:40.456 +0530",
				"message": "[windowsKey]r",
				"scriptName": "HongKong_Scenario.script",
				"handlerLine": 3,
				"identifier": "typetext"
			},
		{
				"handlerName": "on_launch",
				"timestamp": "2022-03-01 16:35:51.650 +0530",
				"scriptName": "HongKong_Scenario.script",
				"message": "found at (262, 996)",
				"image": "(TEXT:\"Cancel\")",
				"handlerLine": 4,
				"identifier": "waitfor"
			},
		{
				"handlerName": "on_launch",
				"timestamp": "2022-03-01 16:35:53.530 +0530",
				"message": "Chrome https://staging.dentsplysirona.com/en-hk/shop[return]",
				"scriptName": "HongKong_Scenario.script",
				"handlerLine": 5,
				"identifier": "typetext"
			},
		{
				"handlerName": "on_launch",
				"timestamp": "2022-03-01 16:36:44.885 +0530",
				"scriptName": "HongKong_Scenario.script",
				"message": "Unable to Find Image (TEXT:\"Yes, I am\"). Text not found.",
				"image": "(TEXT:\"Yes, I am\")",
				"handlerLine": 6,
				"identifier": "imagefound"
			},
		{
				"handlerName": "on_launch",
				"timestamp": "2022-03-01 16:36:44.916 +0530",
				"message": "Changing to Global site popup is not displaying",
				"scriptName": "HongKong_Scenario.script",
				"handlerLine": 9,
				"identifier": "Log"
			},
		{
				"handlerName": "on_globalpopup",
				"timestamp": "2022-03-01 16:37:18.276 +0530",
				"scriptName": "HongKong_Scenario.script",
				"message": "Unable to Find Image (TEXT:\"Do you want to change to Dentsply Sirona global site\"). Text not found.",
				"image": "(TEXT:\"Do you want to change to Dentsply Sirona global site\")",
				"handlerLine": 2,
				"identifier": "imagefound"
			},
		{
				"handlerName": "on_globalpopup",
				"timestamp": "2022-03-01 16:37:18.346 +0530",
				"message": "Changing to Global site popup is not displaying",
				"scriptName": "HongKong_Scenario.script",
				"handlerLine": 5,
				"identifier": "Log"
			},
		{
				"handlerName": "on_signin",
				"timestamp": "2022-03-01 16:37:18.976 +0530",
				"scriptName": "HongKong_Scenario.script",
				"message": "at (1525, 126)",
				"image": "UserIcon",
				"handlerLine": 2,
				"identifier": "click"
			},
		{
				"handlerName": "on_signin",
				"timestamp": "2022-03-01 16:37:52.056 +0530",
				"scriptName": "HongKong_Scenario.script",
				"message": "found at (670, 353)",
				"image": "(TEXT:\"Welcome\")",
				"handlerLine": 3,
				"identifier": "waitfor"
			},
		{
				"message": "(Duration:\"135.159\", Errors:\"1\", Exceptions:\"0\", StartTime:\"2022-03-01 16:35:40 +0530\", Successes:\"0\", TestCase:\"Master2_HongKong.script\", Warnings:\"0\")",
				"identifier": "EndTestCase",
				"timestamp": "2022-03-01 16:37:55.378 +0530"
			},
		{
				"image": "Screen_Error.png",
				"message": "NoWebDriver: FindElement function must be called with (or on) a WebDriver (or WebElement) object. -- Execution Time 0:02:15 Master2_HongKong.script",
				"identifier": "FAILURE",
				"timestamp": "2022-03-01 16:37:55.718 +0530"
			}
	],
	"createdTimestamp": "2022-03-01 16:35:40.219 +0530"
}